Gkwebdav/__init__.py
Gkwebdav/__version__.py
Gkwebdav/core.py
Gkwebdav-0.0.2.dist-info/LICENSE
Gkwebdav-0.0.2.dist-info/METADATA
Gkwebdav-0.0.2.dist-info/WHEEL
Gkwebdav-0.0.2.dist-info/top_level.txt
Gkwebdav-0.0.2.dist-info/RECORD
